PokeCodePy_Library/__init__.py
PokeCodePy_Library/main.py
PokeCodePy_Library/pokemon.csv
PokeCodePy_Library/random_pokemon.py
PokeCodePy_Library-1.2.2.dist-info/METADATA
PokeCodePy_Library-1.2.2.dist-info/WHEEL
PokeCodePy_Library-1.2.2.dist-info/top_level.txt
PokeCodePy_Library-1.2.2.dist-info/RECORD
